optimus/__init__.py
optimus/_mpu/__init__.py
optimus/_mpu/cross_entropy.py
optimus/_mpu/data.py
optimus/_mpu/initialize.py
optimus/_mpu/layers.py
optimus/_mpu/lora.py
optimus/_mpu/mappings.py
optimus/_mpu/random.py
optimus/_mpu/utils.py
optimus/fused_kernels/__init__.py
optimus/fused_kernels/compat.h
optimus/fused_kernels/scaled_masked_softmax.cpp
optimus/fused_kernels/scaled_masked_softmax.h
optimus/fused_kernels/scaled_masked_softmax_cuda.cu
optimus/fused_kernels/scaled_upper_triang_masked_softmax.cpp
optimus/fused_kernels/scaled_upper_triang_masked_softmax.h
optimus/fused_kernels/scaled_upper_triang_masked_softmax_cuda.cu
optimus/fused_kernels/setup.py
optimus/fused_kernels/tests/test_fused_kernels.py
optimus/fused_kernels/type_shim.h
optimus/generator/__init__.py
optimus/generator/generator.py
optimus/generator/generator_pipeline.py
optimus/hf/__init__.py
optimus/hf/aquila/model_utils.py
optimus/hf/aquila/modeling_aquila_hf.py
optimus/hf/aquila/predict.py
optimus/hf/baichuan/__init__.py
optimus/hf/baichuan/baichuan.py
optimus/hf/baichuan/tokenization_baichuan.py
optimus/hf/deberta/__init__.py
optimus/hf/deberta/deberta.py
optimus/hf/deberta/modeling_deberta.py
optimus/hf/deberta/modeling_deberta_rm_dev.py
optimus/hf/internlm/__init__.py
optimus/hf/internlm/tokenization_internlm.py
optimus/hf/llama/__init__.py
optimus/hf/llama/llama.py
optimus/hf/llama/llama_packing.py
optimus/hf/llama/llama_packing_pipe.py
optimus/hf/llama/llama_pipe.py
optimus/hf/llama/llama_rm_hf.py
optimus/hf/qwen/__init__.py
optimus/hf/qwen/modeling_qwen_hf.py
optimus/hf/qwen/tokenization_qwen.py
optimus/hf/unimc/__init__.py
optimus/hf/unimc/tokenization_unimc.py
optimus/hf/unimc/unimc.py
optimus/hf/yi/__init__.py
optimus/hf/yi/configuration_yi.py
optimus/hf/yi/tokenization_yi.py
optimus/model/__init__.py
optimus/model/activations.py
optimus/model/attention.py
optimus/model/fused_bias_dropout.py
optimus/model/fused_softmax.py
optimus/model/gmlp.py
optimus/model/gpt2_model.py
optimis-0.1.0.dist-info/METADATA
optimis-0.1.0.dist-info/WHEEL
optimis-0.1.0.dist-info/RECORD
